README.md
setup.cfg
setup.py
distributions/Binomialdistribution.py
distributions/Gaussiandistribution.py
distributions/Generaldistribution.py
distributions/__init__.py
haowu_distributions.egg-info/PKG-INFO
haowu_distributions.egg-info/SOURCES.txt
haowu_distributions.egg-info/dependency_links.txt
haowu_distributions.egg-info/not-zip-safe
haowu_distributions.egg-info/top_level.txt