Metadata-Version: 1.0
Name: haowu-distributions
Version: 0.1
Summary: Gaussian and Binomial distributions
Home-page: UNKNOWN
Author: Hao Wu
Author-email: haowu@nyu.edu
License: UNKNOWN
Platform: UNKNOWN
